pysequen/__init__.py
pysequen/blockingdeque.py
pysequen/events.py
pysequen/sequencedpool.py
pysequen-0.1.dist-info/DESCRIPTION.rst
pysequen-0.1.dist-info/METADATA
pysequen-0.1.dist-info/RECORD
pysequen-0.1.dist-info/WHEEL
pysequen-0.1.dist-info/metadata.json
pysequen-0.1.dist-info/top_level.txt
