Metadata-Version: 2.0
Name: pysequen
Version: 0.1
Summary: Python library for concurrent processing of tasks with dependencies requiring sequencing
Home-page: https://github.com/mikecoop83/pysequen/
Author: Michael Coopersmith
Author-email: mikecoop83@gmail.com
License: MIT
Platform: UNKNOWN
